{"run_number": "1776564394956827", "step_name": "train_model", "task_id": "3", "attempt_id": 0, "name": "_current_step", "content_type": "gzip+pickle-v4", "type": "metaflow.artifact", "sha": "d4803470985c29b2a572349115a12213eeac0667", "ds_type": "local", "location": ":root:/home/loother/cinvestav/cinvestav_machine_learning/.metaflow", "flow_id": "ChurnModelFlow", "user_name": "loother", "tags": [], "system_tags": ["user:loother", "metaflow_version:2.19.21", "runtime:dev", "python_version:3.12.3"], "ts_epoch": 1776564400681}